logging_opentracing
