Metadata-Version: 2.1
Name: logging-opentracing
Version: 0.1.2
Summary: OpenTracing handler for the Python logging library
Home-page: https://github.com/kornerc/python-logging-opentracing
Author: Clemens Korner
License: MIT
Platform: any
Classifier: Development Status :: 4 - Beta
Classifier: Intended Audience :: Developers
Classifier: License :: OSI Approved :: MIT License
Classifier: Programming Language :: Python :: 3.6
Classifier: Programming Language :: Python :: 3.7
Classifier: Programming Language :: Python :: 3.8
Classifier: Topic :: Software Development :: Libraries :: Python Modules
